setup.py
geventreactor/__init__.py
geventreactor.egg-info/PKG-INFO
geventreactor.egg-info/SOURCES.txt
geventreactor.egg-info/dependency_links.txt
geventreactor.egg-info/requires.txt
geventreactor.egg-info/top_level.txt