Metadata-Version: 1.0
Name: geventreactor
Version: 0.1.0
Summary: Twisted reactor based on gevent
Home-page: http://github.com/jyio/geventreactor
Author: Jiang Yio
Author-email: inportb@gmail.com
License: MIT
Platform: UNKNOWN
